tempo/__init__.py
tempo/embed.py
tempo/main_multi_6domain_release.py
tempo/run_TEMPO_demo.py
tempo/test_multi_6domain_release.py
tempo/train_TEMPO.py
tempo/train_TEMPO_parallel.py
tempo/data_provider/__init__.py
tempo/data_provider/data_factory.py
tempo/data_provider/data_loader.py
tempo/layers/AutoCorrelation.py
tempo/layers/Autoformer_EncDec.py
tempo/layers/Conv_Blocks.py
tempo/layers/ETSformer_EncDec.py
tempo/layers/Embed.py
tempo/layers/FourierCorrelation.py
tempo/layers/MultiWaveletCorrelation.py
tempo/layers/Pyraformer_EncDec.py
tempo/layers/SelfAttention_Family.py
tempo/layers/Transformer_EncDec.py
tempo/layers/__init__.py
tempo/models/DLinear.py
tempo/models/ETSformer.py
tempo/models/FEDformer.py
tempo/models/GPT4TS.py
tempo/models/PatchTST.py
tempo/models/T5.py
tempo/models/TEMPO.py
tempo/models/__init__.py
tempo/models/autoformer.py
tempo/models/basic_model.py
tempo/models/components/__init__.py
tempo/models/components/base.py
tempo/models/components/beta.py
tempo/models/components/conv.py
tempo/models/components/dense_nn.py
tempo/models/components/flow.py
tempo/models/components/keypoint.py
tempo/models/components/linear.py
tempo/models/components/mlp.py
tempo/models/components/spline.py
tempo/models/components/tc.py
tempo/models/components/transforms.py
tempo/models/components/transition.py
tempo/models/components/utils.py
tempo/models/metrics/__init__.py
tempo/models/metrics/block.py
tempo/models/metrics/correlation.py
tempo/models/metrics/munkres.py
tempo/utils/__init__.py
tempo/utils/metrics.py
tempo/utils/rev_in.py
tempo/utils/timefeatures.py
tempo/utils/tools.py
tempodev-0.0.9.dist-info/LICENSE
tempodev-0.0.9.dist-info/METADATA
tempodev-0.0.9.dist-info/WHEEL
tempodev-0.0.9.dist-info/top_level.txt
tempodev-0.0.9.dist-info/RECORD
